ambition_screening/__init__.py
ambition_screening/admin.py
ambition_screening/admin_site.py
ambition_screening/apps.py
ambition_screening/choices.py
ambition_screening/early_withdrawal_evaluator.py
ambition_screening/eligibility.py
ambition_screening/gender_evaluator.py
ambition_screening/identifiers.py
ambition_screening/mommy_recipes.py
ambition_screening/offline_models.py
ambition_screening/reportables.py
ambition_screening/subject_screening_eligibility.py
ambition_screening/urls.py
ambition_screening/wsgi.py
ambition_screening/forms/__init__.py
ambition_screening/forms/subject_screening_form.py
ambition_screening/migrations/0001_initial.py
ambition_screening/migrations/0002_auto_20180706_1519.py
ambition_screening/migrations/0003_auto_20181108_0353.py
ambition_screening/migrations/0004_auto_20190201_0446.py
ambition_screening/migrations/0005_auto_20190305_0123.py
ambition_screening/migrations/0006_auto_20191002_2313.py
ambition_screening/migrations/0007_auto_20191108_0752.py
ambition_screening/migrations/__init__.py
ambition_screening/models/__init__.py
ambition_screening/models/signals.py
ambition_screening/models/subject_screening.py
ambition_screening/tests/__init__.py
ambition_screening/tests/models.py
ambition_screening/tests/test_age_evaluator.py
ambition_screening/tests/test_early_withdrawal_evaluator.py
ambition_screening/tests/test_eligibility.py
ambition_screening/tests/test_gender_evaluator.py
ambition_screening/tests/test_natural_keys.py
ambition_screening/tests/test_screening_identifier.py
ambition_screening/tests/test_subject_screening.py
ambition_screening/tests/test_subject_screening_form.py
ambition_screening-0.1.40.dist-info/AUTHORS
ambition_screening-0.1.40.dist-info/LICENSE
ambition_screening-0.1.40.dist-info/METADATA
ambition_screening-0.1.40.dist-info/WHEEL
ambition_screening-0.1.40.dist-info/top_level.txt
ambition_screening-0.1.40.dist-info/RECORD
