Metadata-Version: 2.1
Name: ambition-screening
Version: 0.1.40
Summary: Determine a subject's eligibility for ambition/edc.
Home-page: https://github.com/ambition-trial/ambition-screening
Author: Erik van Widenfelt
Author-email: erikvW@gmail.com
License: GPL license, see LICENSE
Keywords: django ambition eligibility edc clinical trials
Platform: UNKNOWN
Classifier: Environment :: Web Environment
Classifier: Framework :: Django
Classifier: Intended Audience :: Developers
Classifier: Intended Audience :: Science/Research
Classifier: License :: OSI Approved :: GNU General Public License v3 (GPLv3)
Classifier: Operating System :: OS Independent
Classifier: Programming Language :: Python :: 3.7
Classifier: Topic :: Internet :: WWW/HTTP
Classifier: Topic :: Internet :: WWW/HTTP :: Dynamic Content
Requires-Python: >=3.7
Requires-Dist: ambition-form-validators
Requires-Dist: ambition-visit-schedule
Requires-Dist: django-collect-offline
Requires-Dist: django-collect-offline-files
Requires-Dist: edc-constants
Requires-Dist: edc-identifier
Requires-Dist: edc-facility
Requires-Dist: edc-form-validators
Requires-Dist: edc-metadata
Requires-Dist: edc-model-admin
Requires-Dist: edc-reportable
Requires-Dist: edc-screening
Requires-Dist: edc-search
